frequenz/client/weather/__init__.py
frequenz/client/weather/_client.py
frequenz/client/weather/_types.py
frequenz/client/weather/conftest.py
frequenz/client/weather/py.typed
frequenz/client/weather/cli/__main__.py
frequenz_client_weather-0.3.1.dist-info/licenses/LICENSE
frequenz_client_weather-0.3.1.dist-info/METADATA
frequenz_client_weather-0.3.1.dist-info/WHEEL
frequenz_client_weather-0.3.1.dist-info/entry_points.txt
frequenz_client_weather-0.3.1.dist-info/top_level.txt
frequenz_client_weather-0.3.1.dist-info/RECORD
