Metadata-Version: 2.4
Name: frequenz-client-weather
Version: 0.3.1
Summary: Weather API Client for Python
Author-email: Frequenz Energy-as-a-Service GmbH <floss@frequenz.com>
License: MIT
Project-URL: Documentation, https://frequenz-floss.github.io/frequenz-client-weather-python/
Project-URL: Changelog, https://github.com/frequenz-floss/frequenz-client-weather-python/releases
Project-URL: Issues, https://github.com/frequenz-floss/frequenz-client-weather-python/issues
Project-URL: Repository, https://github.com/frequenz-floss/frequenz-client-weather-python
Project-URL: Support, https://github.com/frequenz-floss/frequenz-client-weather-python/discussions/categories/support
Keywords: frequenz,python,lib,library,client-weather
Classifier: Development Status :: 3 - Alpha
Classifier: Intended Audience :: Developers
Classifier: License :: OSI Approved :: MIT License
Classifier: Programming Language :: Python :: 3
Classifier: Programming Language :: Python :: 3 :: Only
Classifier: Topic :: Software Development :: Libraries
Classifier: Typing :: Typed
Requires-Python: <4,>=3.11
License-File: LICENSE
Requires-Dist: typing-extensions<5,>=4.12.2
Requires-Dist: numpy<3,>=1.26.4
Requires-Dist: frequenz-api-common<1,>=0.8.0
Requires-Dist: googleapis-common-protos<2,>=1.70.0
Requires-Dist: frequenz-channels<2,>=1.6.1
Requires-Dist: frequenz-client-base<0.12,>=0.11.0
Requires-Dist: frequenz-api-weather<0.15.0,>=0.14.0
Provides-Extra: dev-flake8
Requires-Dist: flake8==7.3.0; extra == "dev-flake8"
Requires-Dist: flake8-docstrings==1.7.0; extra == "dev-flake8"
Requires-Dist: flake8-pyproject==1.2.3; extra == "dev-flake8"
Requires-Dist: pydoclint==0.6.6; extra == "dev-flake8"
Requires-Dist: pydocstyle==6.3.0; extra == "dev-flake8"
Provides-Extra: dev-formatting
Requires-Dist: black==25.1.0; extra == "dev-formatting"
Requires-Dist: isort==6.0.1; extra == "dev-formatting"
Provides-Extra: dev-mkdocs
Requires-Dist: Markdown==3.8.2; extra == "dev-mkdocs"
Requires-Dist: black==25.1.0; extra == "dev-mkdocs"
Requires-Dist: mike==2.1.3; extra == "dev-mkdocs"
Requires-Dist: mkdocs-gen-files==0.5.0; extra == "dev-mkdocs"
Requires-Dist: mkdocs-literate-nav==0.6.2; extra == "dev-mkdocs"
Requires-Dist: mkdocs-macros-plugin==1.3.7; extra == "dev-mkdocs"
Requires-Dist: mkdocs-material==9.6.16; extra == "dev-mkdocs"
Requires-Dist: mkdocstrings[python]==0.30.0; extra == "dev-mkdocs"
Requires-Dist: mkdocstrings-python==1.16.12; extra == "dev-mkdocs"
Requires-Dist: frequenz-repo-config[lib]==0.13.5; extra == "dev-mkdocs"
Provides-Extra: dev-mypy
Requires-Dist: mypy==1.17.1; extra == "dev-mypy"
Requires-Dist: types-Markdown==3.8.0.20250415; extra == "dev-mypy"
Requires-Dist: types-protobuf==6.30.2.20250703; extra == "dev-mypy"
Requires-Dist: frequenz-client-weather[dev-mkdocs,dev-noxfile,dev-pytest]; extra == "dev-mypy"
Provides-Extra: dev-noxfile
Requires-Dist: nox==2025.5.1; extra == "dev-noxfile"
Requires-Dist: frequenz-repo-config[lib]==0.13.5; extra == "dev-noxfile"
Provides-Extra: dev-pylint
Requires-Dist: frequenz-client-weather[dev-mkdocs,dev-noxfile,dev-pytest]; extra == "dev-pylint"
Provides-Extra: dev-pytest
Requires-Dist: pytest==8.4.1; extra == "dev-pytest"
Requires-Dist: pylint==3.3.7; extra == "dev-pytest"
Requires-Dist: frequenz-repo-config[extra-lint-examples]==0.13.5; extra == "dev-pytest"
Requires-Dist: pytest-mock==3.14.1; extra == "dev-pytest"
Requires-Dist: pytest-asyncio==1.1.0; extra == "dev-pytest"
Requires-Dist: async-solipsism==0.8; extra == "dev-pytest"
Provides-Extra: dev
Requires-Dist: frequenz-client-weather[dev-flake8,dev-formatting,dev-mkdocs,dev-mypy,dev-noxfile,dev-pylint,dev-pytest]; extra == "dev"
Dynamic: license-file
